MANIFEST.in
README.rst
setup.py
kungfu/__init__.py
kungfu/kungfu.py
kungfu/prepublish.py
kungfu/version.py
kungfu.egg-info/PKG-INFO
kungfu.egg-info/SOURCES.txt
kungfu.egg-info/dependency_links.txt
kungfu.egg-info/requires.txt
kungfu.egg-info/top_level.txt