Metadata-Version: 1.1
Name: kungfu
Version: 1.5.9
Summary: A Pandas Enhancement
Home-page: https://pypi.python.org/pypi/kungfu
Author: Jerry
Author-email: jerryzhujian9@gmail.com
License: MIT
Keywords: scipy,numpy,pandas,kungfu,array,matlab,matrix,cell,cross-platform,quick,easy,wrapper
Platform: UNKNOWN
Classifier: Development Status :: 3 - Alpha
Classifier: Intended Audience :: Developers
Classifier: Topic :: Software Development :: Build Tools
Classifier: License :: OSI Approved :: MIT License
Classifier: Programming Language :: Python :: 2.7
